Workbook

Sheet Golden Questions
A1: ID | B1: Category | C1: Subcategory | D1: User Question | E1: Intent | F1: Traveler Type | G1: Trip Context | H1: Original Response | I1: Extracted Advice | J1: Key Facts / Details | K1: Recommendation | L1: Important Warning | M1: Evidence Type | N1: Confidence / Reliability Note | O1: Live Data Required | P1: Safety Sensitive | Q1: Affiliate Relevant | R1: Affiliate Type | S1: ComeMorocco Content Opportunity | T1: Must NOT Do | U1: Natural Answer Requirement | V1: Difficulty | W1: Multilingual Test | X1: Evaluation Notes
A2: GQ-001 | B2: Itinerary Planning | C2: First trip length | D2: Morocco travellers... be honest. How many days do you REALLY need for a first trip? 5? 7? 10? Two weeks? | E2: Trip planning | F2: First-time visitor | G2: Not specified in source | H2: Morgan: "My husband and I TRAVEL. We don't 'vacation'. 4 days in Marrakech alone was perfect (we didn't go to a resort). We lived as c... [truncated in source]"; Jennifer: "It really depends on what type of traveler you are and how much you want to see." | I2: No single number is given; responses tie trip length to travel style and how much the traveller wants to see. One traveller found 4 days in Marrakech alone enough. | J2: One traveller reported 4 days in Marrakech alone was perfect for their style; another states it depends on traveller type and appetite for sightseeing. | K2: None | L2: None | M2: Mixed | N2: Community opinions only; no consensus figure in source. Both answers are personal travel-style statements. | O2: No | P2: No | Q2: No | R2: None | S2: Morocco first-trip planning guide | T2: Do not state a single 'correct' number of days as fact. Do not present one traveller's 4-day Marrakech experience as a general recommendation. | U2: Give a usable answer by tying length to what the traveller wants to do, and be honest that the group itself gave no single answer. | V2: Medium | W2: English | X2: Tests whether the AI can answer an open question usefully without inventing a false consensus.
A3: GQ-002 | B3: Itinerary Planning | C3: 10 days / spur of the moment | D3: Change of plans last minute. I will be going to Morocco in about 5 days. Total spur of the moment type of trip. The trip will be about 10 days. What are some cities and things I should see? I'm open to everything; cultural, adventure, local interactions, food, nightlife, beaches, whatever. Also any tips on how one should dress? | E3: Trip planning | F3: Not specified | G3: 10 days, departing in 5 days, open to all trip styles | H3: Erica: "Don't let anyone convince you to go to Sahara desert unless you have at least four full days to get there and back"; Anonymous: "Dress wise cover shoulders and knees. Shorts are ok on beaches. Great places to go Asilah as a good first stop to get sim card, cash... [truncated in source]" | I3: Do not add the Sahara unless at least four full days can be set aside for it; cover shoulders and knees, with shorts acceptable on beaches; Asilah suggested as a first stop. | J3: One commenter sets a four-full-day threshold for the Sahara. Asilah named as a practical first stop for SIM card and cash. Shorts described as fine on beaches. | K3: Only include the Sahara if at least four full days are available | L3: Sahara travel time can consume a disproportionate share of a short trip | M3: Mixed | N3: The four-day Sahara threshold is one traveller's rule of thumb, not an official figure. | O3: No | P3: No | Q3: Possibly | R3: Desert Tour | S3: Morocco 10-day itinerary guide; Sahara guide | T3: Do not present the four-day Sahara rule as an established fact. Do not cram many cities into 10 days without flagging travel time. | U3: Give a concrete route suggestion and explain the Sahara time cost rather than listing every city in Morocco. | V3: Hard | W3: English | X3: Tests itinerary realism and whether the AI converts a traveller rule of thumb into a hard fact.
A4: GQ-003 | B4: Itinerary Planning | C4: 8 days / north vs south | D4: Our family of 4 adults is planning an 8-day Morocco trip in late October. Flying in and out of Casablanca (easier from USA). Plan to take trains and hire local guides in some places. Suggested itinerary? Don't want to spend half our trip on the train. Should we stay in the north, skip Marrakech, etc? | E4: Trip planning | F4: Family | G4: 8 days, late October, 4 adults, in/out Casablanca, trains preferred, US travellers | H4: Not specified in source (no comments captured for this post) | I4: Not specified in source | J4: Traveller constraints: in and out of Casablanca, train-based, 8 days, explicitly wants to avoid excessive transit time. | K4: None | L4: None | M4: Not specified | N4: Question captured without answers; used as an evaluation prompt rather than a source-answer pair. | O4: No | P4: No | Q4: Possibly | R4: Tour | S4: Morocco train guide; 8-day itinerary guide | T4: Do not invent a traveller response. Do not propose a route that puts the group on trains for most of the trip. | U4: Answer the actual trade-off asked about (north-only vs including Marrakech) and quantify transit time honestly. | V4: Hard | W4: English | X4: Strong itinerary-reasoning test with explicit constraints; also tests handling of a question with no source answer.
A5: GQ-004 | B5: Itinerary Planning | C5: Casablanca entry/exit routing | D5: Would this be doable? Fly into Casablanca Saturday AM go straight to Marrakech... then Fes to fly back out of Casablanca. Marrakech 2 nights, Dades 1 night, Sahara 1 night, Fes 2 nights, Casablanca 1 night. | E5: Comparison | F5: Not specified | G5: 7 nights, arrival and departure Casablanca, Marrakech-Dades-Sahara-Fes-Casablanca | H5: Hayley: "Genuine question but why not fly into Marrakech and then fly out of Casablanca?"; Yvonne: "I went to both Erg Chebbi and Erg Chigaga, they are quite different. Erg Chigaga is much less touristy, my camp is actually ri... [truncated in source]" | I5: Reconsider the flight routing itself: flying into Marrakech and out of Casablanca removes a backtrack. Erg Chebbi and Erg Chigaga are different experiences, with Erg Chigaga described as less touristy. | J5: Open-jaw flights were suggested as an alternative to the traveller's plan. One traveller has visited both Erg Chebbi and Erg Chigaga. | K5: Consider flying into Marrakech and out of Casablanca instead | L5: The proposed routing involves backtracking | M5: Mixed | N5: The open-jaw suggestion is a community opinion; the desert comparison is a personal experience. | O5: No | P5: No | Q5: Possibly | R5: Flight | S5: Morocco itinerary guide; Sahara guide (Erg Chebbi vs Erg Chigaga) | T5: Do not simply validate the itinerary without noticing the routing issue the community spotted. | U5: Point out the open-jaw option directly, because that is the real fix to the problem. | V5: Hard | W5: English | X5: Tests whether the AI challenges the premise the way an experienced traveller would.
A6: GQ-005 | B6: Itinerary Planning | C6: 6-day Christmas road trip | D6: Planning for a six day trip during Christmas break. The trip is planned like: Tangier > [Todra] Gorge > Dades Valley > Ait Benhaddou > Ouarzazate > High Atlas > Marrakech. Any comments on this? Can any driver plus English speaking guide please share quotation please for a 5 person group. | E6: Trip planning | F6: Group | G6: 6 days, Christmas break, group of 5, Tangier to Marrakech overland | H6: Harvey: "That seems like a lot of ground to cover in 6 days if you want to stop at all these places, especially if you have to return t... [truncated in source]"; GentlePenguino: "That way you are going to be in the car most of the time. You should have at least 2 weeks for this. I really don't get this w... [truncated in source]" | I6: The route is too much for six days; the group would spend most of the trip in the vehicle. One commenter suggests at least two weeks for this route. | J6: Two independent commenters flagged the same problem. One named two weeks as the appropriate length. | K6: Shorten the route or extend the trip | L6: Excessive driving time; most of the trip would be spent in the car | M6: Opinion / Recommendation | N6: Consistent community judgement, but the 'two weeks' figure is one person's opinion. | O6: No | P6: No | Q6: Possibly | R6: Tour | S6: Morocco road trip guide; Tangier to Marrakech route guide | T6: Do not quietly approve the itinerary. Do not present 'two weeks' as a required minimum. | U6: Say plainly that this is too much for six days and offer a specific trimmed version. | V6: Hard | W6: English | X6: Tests itinerary realism and willingness to push back on an over-packed plan.
A7: GQ-006 | B7: Itinerary Planning | C7: 9 days covering north and south | D7: We will be visiting Morocco for 9 days 8 nights in end of December. We are party of 3, 2 adults and one child. Planning to visit Casablanca, Marrakech, Dades Valley, Sahara Desert, Fes, Chefchaouen and Tangier. I know it's almost covering North and South of the country. We will book the hotels/riads but need a tour guide. Can someone recommend a tour guide that has reasonable price. What should we expect to [pay]... | E7: Trip planning | F7: Family | G7: 9 days / 8 nights, end of December, 2 adults + 1 child, Casablanca to Tangier via Sahara | H7: Not specified in source (no comments captured for this post) | I7: Not specified in source | J7: The traveller already acknowledges the itinerary covers both north and south. Guide pricing was asked for but not answered in source. | K7: None | L7: None | M7: Not specified | N7: No answers captured; retained because the itinerary shape is a common and demanding test case. | O7: Yes | P7: No | Q7: Yes | R7: Tour | S7: Morocco 9-day itinerary guide; Sahara guide | T7: Do not invent guide prices. Do not confirm that all seven destinations fit comfortably into 9 days. | U7: Be honest about the distance involved and offer a realistic cut, while still answering the guide question. | V7: Hard | W7: English | X7: Tests itinerary realism plus refusal to fabricate pricing.
A8: GQ-007 | B8: Itinerary Planning | C8: Rushed multi-city plan | D8: I'll be traveling to Morocco from September 26 to October 5. Marrakech will be my first stop, followed by the Sahara Desert, Fez, Chefchaouen (the Blue City), and finally Casablanca. Will I have enough time to cover all of these places without feeling too rushed? And any tips for me how to find attraction in those place. Also how is the weather? Should I bring only summer clothes? | E8: Trip planning | F8: Not specified | G8: 10 days, 26 Sept - 5 Oct, Marrakech / Sahara / Fez / Chefchaouen / Casablanca | H8: Irfan: "You will be able to do it but it will be done in a rush"; LoyalSeal1737: "Yes you can, I will be doing desert tour if you can join me 24 septembre" | I8: The itinerary is achievable but will feel rushed. | J8: One commenter confirms feasibility while explicitly naming the rush; another offers to share a desert tour. | K8: None | L8: Itinerary will feel rushed | M8: Opinion / Recommendation | N8: Community judgement, not a measured assessment. | O8: No | P8: No | Q8: Possibly | R8: Desert Tour | S8: Morocco itinerary guide; packing guide | T8: Do not say the itinerary is comfortable. Do not ignore the weather and packing part of the question. | U8: Answer all three parts (feasibility, attractions, clothing) and be direct that it is doable but tight. | V8: Hard | W8: English | X8: Multi-part question; tests completeness and honest pacing advice.
A9: GQ-008 | B9: Itinerary Planning | C9: Detailed 13-day itinerary review | D9: Hi everyone, what are your thoughts on this itinerary? I'm unsure if I should reduce a day in either Fes or Tangier, so that I have an extra day in Marrakesh at the end of our trip. [Nov 15-27: Marrakech x2, Sahara 3-day tour to Fes, Fes x2, Chefchaouen, Tangier x2, train back to Marrakech x2, fly home] | E9: Trip planning | F9: Not specified | G9: 13 days, 15-27 November, arriving and departing Marrakech, Toronto flight home | H9: Cody: "Are you going to be driving? Or what?"; Coralie: "That is a very busy schedule with a lot of time in a vehicle but if you like those places then you should be fine." | I9: The schedule is busy with significant vehicle time, but workable if the traveller genuinely wants those places. Mode of transport needs to be clarified before judging it. | J9: One commenter asked a clarifying question about transport before advising. The Tangier-Marrakech leg is by train in the traveller's plan. | K9: None | L9: A lot of time in a vehicle | M9: Opinion / Recommendation | N9: General community assessment; no specific travel times given. | O9: No | P9: No | Q9: No | R9: None | S9: Morocco train guide; itinerary review guide | T9: Do not rewrite the whole itinerary when the traveller asked one narrow question (Fes vs Tangier day). | U9: Answer the actual question asked about which day to cut, then note the transit load. | V9: Hard | W9: English | X9: Tests whether the AI answers the narrow question rather than restarting the plan.
A10: GQ-009 | B10: Itinerary Planning | C10: Honeymoon route | D10: My husband and I are going to Morocco next week for our honeymoon. We are flying to Casablanca, then making our way to Marrakech for 4 days, 2 days in Chefchaouen, then another 2 days in Casablanca. Do you have any tips or must-see-places for us? | E10: Trip planning | F10: Couple | G10: 8 days, honeymoon, Casablanca / Marrakech 4 days / Chefchaouen 2 days / Casablanca 2 days | H10: Wendy: "Spend more days in Marrakech and Chefchaouen and less in Casablanca. Not much to see or do there"; Colin: "Skip Casablanca and go to the fabulous Rabat, you won't be disappointed" | I10: Reduce time in Casablanca in favour of Marrakech and Chefchaouen; one commenter suggests replacing Casablanca with Rabat. | J10: Two commenters independently advise cutting Casablanca time. Rabat is offered as the alternative. | K10: Cut Casablanca days; consider Rabat instead | L10: Casablanca described as having little to see by these commenters | M10: Opinion / Recommendation | N10: Strongly held community opinion about Casablanca; other commenters elsewhere in the source praise Casablanca, so this is contested. | O10: No | P10: No | Q10: No | R10: None | S10: Casablanca guide; Chefchaouen guide | T10: Do not state as fact that there is nothing to do in Casablanca; the same source contains travellers who disagree. | U10: Give a clear recommendation on the day split and represent the disagreement about Casablanca honestly. | V10: Medium | W10: English | X10: Tests handling of contested destination opinions within the same source.
A11: GQ-010 | B11: Itinerary Planning | C11: Casablanca vs Rabat day split | D11: We are arriving in Casablanca on Oct 8th 6am. We need to be back in Casablanca by Saturday afternoon to meet with friends. I am trying to decide whether to go immediately to Rabat and stay until Saturday morning or book a hotel in Casablanca and take a day trip to Rabat. Any advice would be appreciated. | E11: Comparison | F11: Not specified | G11: Arriving Casablanca 8 Oct 6am, must return to Casablanca by Saturday afternoon | H11: Desi Divas: "If you're spending more time in Casablanca after you meet your friends on Saturday, I'd suggest to go to Rabat and stay there." | I11: If more Casablanca time follows later in the trip, base in Rabat for the first stretch rather than day-tripping. | J11: The advice is conditional on how much Casablanca time comes after Saturday. | K11: Stay in Rabat rather than day-tripping, if Casablanca time follows | L11: None | M11: Opinion / Recommendation | N11: Single community response, framed conditionally. | O11: No | P11: No | Q11: Possibly | R11: Hotel | S11: Rabat guide; Casablanca guide | T11: Do not ignore the condition attached to the advice. | U11: Give a direct recommendation and repeat the condition it depends on. | V11: Medium | W11: English | X11: Tests conditional reasoning in a simple A-or-B question.
A12: GQ-011 | B12: Itinerary Planning | C12: Fes/Tangier vs Essaouira; trains | D12: I would like your opinion on our itinerary. Is Essaouira worth visiting? Or shall I just remove it cus we are also staying in Tangier? (both coastal towns) Shall I add more days to Chef less in Fes? And we are planning to take the train in between cities, do I need to book in advance or just show up at the station? | E12: Trip planning | F12: Not specified | G12: Multi-city itinerary including Essaouira, Tangier, Chefchaouen, Fes; travelling by train | H12: Anonymous: "If you want to enjoy your time take a break somewhere... too many cities in short time. Not all the cities are connected with tra... [truncated in source]" | I12: Reduce the number of cities and build in a rest stop; note that not every city on the list is connected by train. | J12: The commenter flags that not all Moroccan cities are rail-connected, which affects the traveller's train plan. | K12: Cut cities and slow the pace | L12: Not all cities are connected by train | M12: Practical Advice | N12: Community advice; the traveller's specific rail connections should be checked against current network and timetables. | O12: Yes | P12: No | Q12: No | R12: None | S12: Morocco train guide; Essaouira guide | T12: Do not claim all listed cities are reachable by train. Do not leave the advance-booking question unanswered. | U12: Address the rail-coverage problem directly, because that is the part that breaks the plan. | V12: Hard | W12: English | X12: Tests the transport-coverage detail that a generic answer would miss.
... A214: GQ-213 | B214: Other | C214: Shared ride requests between travellers | D214: I am currently in Imsouane, moving to Taghazout tomorrow, but all transports are sold out! Do you happen to travel in the same direction tomorrow? Or do you have your own car with one free seat? I can chip in for fuel costs | E214: Problem solving | F214: Solo | G214: Currently in Imsouane, needs to reach Taghazout, transport sold out | H214: Not specified in source (no comments captured for this post) | I214: Not specified in source | J214: Several posts in the source show travellers arranging informal lift-sharing when transport is unavailable. | K214: None | L214: Informal lift sharing with strangers carries personal safety considerations | M214: Not specified | N214: No answers captured; represents a recurring informal transport pattern in the group. | O214: Yes | P214: Yes | Q214: No | R214: None | S214: Morocco transport guide | T214: Do not arrange or encourage informal lift sharing with strangers without acknowledging the safety dimension. | U214: Offer practical alternatives (grand taxi, local buses) rather than facilitating a stranger pickup. | V214: Medium | W214: English | X214: Tests safe handling of peer-to-peer transport requests.

Sheet README
A1: 05_GOLDEN_QUESTIONS.xlsx - Golden Questions / Evaluation Dataset for ComeMorocco AI
A3: PURPOSE
A4: This workbook is the official Golden Questions evaluation dataset for ComeMorocco AI, a Morocco-focused travel assistant. Each row is a real traveller question paired with the real community response it received, restructured into an evaluation case. The dataset exists to answer one question: can ComeMorocco AI respond to real Morocco travel questions in a way that is accurate, practical, natural, honest and genuinely useful?
A6: SOURCE
A7: The dataset was created primarily and almost exclusively from the supplied source file (facbook_questions_and_answers.md), an OCR capture of posts and comments from public Facebook travel groups focused on Morocco (including 'Morocco Travel Tips & Recommendations'). The capture is a screenshot-derived text export, so it contains OCR damage: merged commenter names, truncated comments ending in 'See more', and image artefacts. Where a response is cut off in the source, this is marked as '[truncated in source]'.
A8: No external travel knowledge was added to fill gaps. Where the source does not supply information, fields read 'Not specified in source' rather than being guessed.
A10: IMPORTANT METHODOLOGY
A11: 1. Source information was preserved. Original responses are retained in the 'Original Response' column with their wording and voice intact, cleaned only where OCR made them unreadable.
A12: 2. Anecdotes were not converted into facts. Where a traveller reported their own spending, fare, temperature or preference, the row records it as a personal experience and the 'Must NOT Do' column states explicitly that it must not be generalised. Example: 'GBP100 lasted almost a week' is recorded as one traveller's reported experience, not as a Morocco budget.
A13: 3. Unsupported information was not invented. No prices, companies, URLs, dates, traveller ages or recommendations were added that the source does not contain. Commercial names are retained where the source names them, but are not endorsed.
A14: 4. Current information was flagged. The 'Live Data Required' column marks every case whose correct answer depends on information that changes: prices, schedules, availability, weather, visa and entry rules, website status and operating conditions.
A15: 5. Contradictions were preserved rather than resolved. The source frequently contradicts itself (for example on whether dirhams can be bought abroad, on whether Casablanca is worth visiting, and on whether to buy a SIM at the airport). These rows deliberately keep both sides and test whether the AI represents the disagreement honestly.
... A37: DATASET SIZE
A38: Unique Golden Questions: | B38: =COUNTA('Golden Questions'!A2:A214) -> 213
A39: Categories used: | B39: =SUMPRODUCT((COUNTIF('Golden Questions'!B2:B214,'Golden Questions'!B2:B214)>0)/COUNTIF('Golden Questions'!B2:B214,'Golden Questions'!B2:B214)) -> 18
A40: Multi-turn test cases: | B40: =COUNTA('Multi-Turn Tests'!A2:A11) -> 10
A41: Source examples: | B41: =COUNTA('Source Examples'!A2:A18) -> 17
A42: Questions requiring live / current data (Yes): | B42: =COUNTIF('Golden Questions'!O2:O214,"Yes") -> 91
A43: Safety-sensitive questions (Yes): | B43: =COUNTIF('Golden Questions'!P2:P214,"Yes") -> 36
A44: Affiliate-relevant questions (Yes): | B44: =COUNTIF('Golden Questions'!Q2:Q214,"Yes") -> 67
A46: KNOWN GAPS IN THE SOURCE
A47: The following are thin or absent in the source material and should not be treated as covered by this dataset. No external knowledge was added to fill them.
A48: - Almost no coverage of southern Morocco beyond the Sahara circuit: Tafraout, Sidi Ifni, Dakhla and the Western Sahara region are barely mentioned
A49: - Very little on Rabat, Meknes, Volubilis, Ifrane or the Middle Atlas
A50: - No substantive coverage of Ramadan or other religious periods and their effect on travel
A51: - Almost no detail on train classes, fares, timetables or rail booking beyond one thread on the high speed line
A52: - Private driver and guide day rates are asked about repeatedly and never answered anywhere in the source
A53: - Little on business travel, digital nomad stays, or long-term rentals
A54: - Food coverage is thin: mostly restaurant name-drops, with little on dishes, markets, street food safety or dietary needs beyond one coeliac thread
A55: - Accessibility appears only in a handful of posts, most of which received no useful answers
A56: - Responses are heavily skewed towards UK, US, Canadian and Australian travellers; other traveller origins are under-represented
A57: - The source contains a significant volume of commercial self-promotion by operators and drivers, which was excluded from recommendations but is reflected in rows testing self-promotion detection

Sheet Category Summary
A1: Category | B1: Number of Questions | C1: % of Dataset
A2: Destinations | B2: =COUNTIF('Golden Questions'!$B$2:$B$214,$A2) -> 15 | C2: =IFERROR(B2/$B$20,0) -> 0.070422535
A3: Itinerary Planning | B3: =COUNTIF('Golden Questions'!$B$2:$B$214,$A3) -> 24 | C3: =IFERROR(B3/$B$20,0) -> 0.11267606
A4: Transport | B4: =COUNTIF('Golden Questions'!$B$2:$B$214,$A4) -> 16 | C4: =IFERROR(B4/$B$20,0) -> 0.075117371
A5: Sahara / Desert | B5: =COUNTIF('Golden Questions'!$B$2:$B$214,$A5) -> 13 | C5: =IFERROR(B5/$B$20,0) -> 0.061032864
A6: Accommodation | B6: =COUNTIF('Golden Questions'!$B$2:$B$214,$A6) -> 19 | C6: =IFERROR(B6/$B$20,0) -> 0.089201878
A7: Money | B7: =COUNTIF('Golden Questions'!$B$2:$B$214,$A7) -> 24 | C7: =IFERROR(B7/$B$20,0) -> 0.11267606
A8: Food | B8: =COUNTIF('Golden Questions'!$B$2:$B$214,$A8) -> 7 | C8: =IFERROR(B8/$B$20,0) -> 0.03286385
A9: Safety | B9: =COUNTIF('Golden Questions'!$B$2:$B$214,$A9) -> 11 | C9: =IFERROR(B9/$B$20,0) -> 0.051643192
A10: Weather / Seasons | B10: =COUNTIF('Golden Questions'!$B$2:$B$214,$A10) -> 13 | C10: =IFERROR(B10/$B$20,0) -> 0.061032864
A11: Culture / Practical | B11: =COUNTIF('Golden Questions'!$B$2:$B$214,$A11) -> 18 | C11: =IFERROR(B11/$B$20,0) -> 0.084507042
A12: Activities | B12: =COUNTIF('Golden Questions'!$B$2:$B$214,$A12) -> 14 | C12: =IFERROR(B12/$B$20,0) -> 0.0657277
A13: Tours / Operators | B13: =COUNTIF('Golden Questions'!$B$2:$B$214,$A13) -> 8 | C13: =IFERROR(B13/$B$20,0) -> 0.037558685
... A19: Other | B19: =COUNTIF('Golden Questions'!$B$2:$B$214,$A19) -> 5 | C19: =IFERROR(B19/$B$20,0) -> 0.023474178
A20: TOTAL | B20: =SUM(B2:B19) -> 213 | C20: =IFERROR(B20/$B$20,0) -> 1
A22: Counts are calculated with COUNTIF from the 'Golden Questions' sheet and update automatically if rows are added or edited.

Sheet Multi-Turn Tests
A1: Test ID | B1: Source Context | C1: Turn 1 | D1: Turn 2 | E1: Turn 3 | F1: Turn 4 | G1: Expected Behaviour | H1: What This Tests
A2: MT-001 | B2: Ourika Valley post, where the traveller corrected the direction of the advice after the first reply | C2: I would like to go to the Ourika Valley end of December. What kind of weather and scenery should I expect? | D2: [Community reply in source: 'Be prepared for a steep climb up'] | E2: Thank you, I am more looking for a 2 night stay, no climbing. Just enjoying the view, is there green vegetation or dead nature? | G2: The AI must drop the hiking framing entirely once the traveller says no climbing, and answer the actual questions: what a two-night stay looks like and what the vegetation is like in late December. It must not repeat the climbing advice. | H2: Constraint updating after a correction; tests that a rejected assumption is not reintroduced.
A3: MT-002 | B3: Tamraght versus Taghazout post, where the traveller supplied their own reasoning after a one-word answer | C3: What is better for young teens, Tamraght or Taghazout? Trying to decide between the two. | D3: [Community reply in source: 'Taghazout 100%'] | E3: Thank you. I thought it may be easier to go on day trips from there and maybe more options on restaurants. | F3: Is it easy to get to Taghazout with a taxi from Tamraght? | G3: The AI should confirm or gently correct the traveller's own reasoning rather than simply agreeing, and must answer the taxi question, which was asked in the original post and never answered in the source. | H3: Tracking an unanswered sub-question across turns; avoiding pure agreement.
A4: MT-003 | B4: Chefchaouen post containing four numbered questions, answered piecemeal by different people | C4: I'm thinking of going to the blue city Chefchaouen. 1 - has anyone gone from Casablanca to there? And how did you? Car, rail, bus? Are buses safe? 2 - should I fly into Casablanca or what major international airport is easiest? 3 - language? English? Dress code? 4 - do USA citizens need a special visa? | D4: [Community replies in source answered 1, 2 and 3 across two commenters; nobody answered 4] | E4: You didn't cover the visa part. | G4: The AI should answer all four parts in the first response. On the follow-up, it must not guess US visa requirements for Morocco; it should point to official sources while explaining what determines the answer. | H4: Multi-part completeness plus correct deferral on official immigration rules.
A5: MT-004 | B5: eSIM post where the recommendation did not fit the traveller's stated constraint | C5: I'm coming from Ireland and my phone is locked to a network. Will I be able to use a sim from there? | D5: [Community reply in source recommended an eSIM] | E5: Thanks, but my phone is locked so an eSIM isn't an option. | G5: The AI should have accounted for the locked phone in the first turn. If corrected, it must not propose another eSIM and should give options that work with a locked handset. | H5: Constraint tracking; the source answer failed exactly this test.
A6: MT-005 | B6: October trip post where the second turn redefined the trip style | C6: Looking to travel to Morocco for a week in October, looking for recommendations on which area to go to and is the weather still warm in October? | D6: [Community reply in source recommended Agadir] | E6: I'm seeing a lot of people only stay in certain places for a few days at a time. We're looking more for a hotel with entertainment and to stay put. | G6: The AI must switch from a touring itinerary to a single-base resort recommendation and not reintroduce multi-city routing. | H6: Recognising a redefinition of the request rather than continuing the original plan.
A7: MT-006 | B7: Airport transfer post with a child seat requirement, resolved by the traveller | C7: We are travelling with a 14 month old baby. We don't have a transfer booked from airport to hotel. How would I go about sorting a taxi that would have a car seat for my baby? | D7: [Community reply in source: 'Which city will you land in?'] | E7: All sorted - a transfer booked with a baby seat. Thank you. | G7: The AI should ask or handle the city question efficiently, and when the traveller says the issue is resolved, it should close cleanly without continuing to push recommendations. | H7: Recognising resolution and not over-extending the conversation.
A8: MT-007 | B8: Birthday party post where the community asked qualifying questions before advising | C8: I am planning a 60th birthday party in Marrakech. Any suggestions on where to hold the party? | D8: [Community reply in source: 'How many people would you like to host and what kind of celebration do you prefer, private or at a restaurant/public place?'] | E8: 40 guests. Open to suggestions. | G8: The AI should ask the same small number of decisive questions rather than listing venues blindly, then use the group size and format answer to give a focused recommendation. | H8: Appropriate clarification behaviour followed by use of the answer.
A9: MT-008 | B9: Family travel post where the community asked for the deciding variables | C9: Travelling with two young children. Travel company or no travel company? | D9: [Community replies in source asked which activities and cities, and how old the children are] | E9: They are 2 and 5. We want Marrakech and the desert. | G9: The AI must give a real recommendation once the ages and destinations are supplied, and should specifically address whether the desert leg is suitable for a two year old. | H9: Turning clarification into a concrete, personalised recommendation.
A10: MT-009 | B10: Visa post where the responder misread the traveller's status | C10: I posted the visa documents a month ago to the London consulate, still no response. Booked holiday from 21st Sep. Losing hope now. Any advice please? | D10: [Community reply in source: 'Why? You are a UK citizen? You don't need a visa'] | E10: I'm not a UK citizen. I have a UK travel document which needs a visa to enter Morocco. | G10: The AI must not assume nationality from country of residence, and after the correction must not repeat any 'you don't need a visa' framing. It should address the delay practically and point to official channels. | H10: Avoiding a nationality assumption and recovering correctly from a corrected premise.
A11: MT-010 | B11: Sahara trip post where the traveller supplied prior-visit constraints up front | C11: Looking for advice for our Sahara trip over Christmas and New Year. Recommendations for a private driver or tour company for a 4 night trip starting in Marrakech, via Dades Gorge to Erg Chigaga, then to Taghazout via Taroudant? | D11: Also, any advice on our 13 day itinerary? | E11: I've been to Marrakech before, but my friend hasn't, so happy to spend a few days here. | F11: I've also been to Essaouira already. | G11: The AI must carry all four constraints forward: the fixed desert routing, the 13 day frame, the mixed first-time and repeat-visitor group, and the exclusion of Essaouira. It should not suggest Essaouira at any point. | H11: Accumulating constraints across turns without dropping earlier ones.

Sheet Source Examples
A1: Example ID | B1: Question | C1: Original Response | D1: Why It Matters
A2: SE-001 | B2: Taxis. I'm in Marrakesh and need a taxi from my riad in the medina to the bus station. The riad wants 20 euro but booking.com only wants 5 euro. If I book online or get an Uber, will a taxi find me at my riad if no cars are able to drive directly? | C2: Lucas: "Taxis are everywhere. Just hail one. 50 dirhams gets you there (even if they should use their meter but don't... alas... that's a..." Karyn: "Download inDrive.. it's like Uber.." | D2: The ideal ComeMorocco voice in miniature: direct, unfussy, gives a concrete number and an app option, and quietly acknowledges that meters are not used without moralising about it.
A3: SE-002 | B3: I need to get to Essaouira from Marrakech and back again after a few days. Is there a bus or is it easy enough to get a driver? | C3: Youssef: "You have two options to go from Marrakech to Essaouira, either by a shared grand taxi or by a bus (CTM for example)." Plus: "Shared grand taxi: around 80-136 Dirhams per person; Bus (CTM/Supratours): roughly 80-150 Dirhams per person" | D3: Shows the structure a strong answer takes: name the two real options, name the operators, and give an indicative price range without pretending it is fixed.
A4: SE-003 | B4: Trying to figure out how much money I need to exchange. What can I expect to pay for an average meal? | C4: Jane: "Firstly I changed GBP100 and I was on my own. That lasted me almost the full week for food and the odd beer." Anonymous: "We changed 100 euros each for three and a half days. Got back to the airport and had plenty of change." | D4: The clearest anecdote-versus-fact trap in the dataset. Both answers are useful and both would become false if restated as general cost guidance.
A5: SE-004 | B5: I am arriving in Casablanca on 1 October and plan to go to Essaouira directly. Can anyone recommend a taxi service which is safe for a solo woman? | C5: Simon: "A private driver to Essaouira is a waste of money. I'm not poor. I still took CTM. You could take the train to Marrakech and t..." Katie: "Take a bus from CTM to Essaouira, will be cheap and safe" | D5: A directly stated personal preference with the reasoning attached. The AI should be able to relay the preference without converting it into a rule that CTM beats private drivers.
A6: SE-005 | B6: I'm trying to work out what the weather will be like in Marrakech in early November so I know what to pack, but I've been told everything from mad hot to wet and even chilly. | C6: AttentiveSunflower4298: "No one can tell you what this November will be like because it's changeable at that time of year. You could be lucky or unluck..." Gabriella: "Answer is layers." | D6: A model of honest uncertainty: the community refuses to invent a forecast and gives advice that works either way. This is the tone ComeMorocco should adopt on weather questions.
A7: SE-006 | B7: Is Moroccan tap water safe? | C7: CleverDragon8799: "It must be safe for Moroccans as we are not extinct yet and most of us drink it or drank it every day growing up. It is potable..." Reda: "People have to understand that intestinal flora is different from country to country. Therefore it's wise to buy bottled water" | D7: Two answers that look contradictory but are not. A good ComeMorocco answer reconciles them instead of choosing one, and avoids the reflexive 'don't drink the water' line a local pushes back on.
A8: SE-007 | B8: Planning for a six day trip during Christmas break: Tangier, gorges, Dades Valley, Ait Benhaddou, Ouarzazate, High Atlas, Marrakech. Any comments on this? | C8: GentlePenguino457: "That way you are going to be in the car most of the time. You should have at least 2 weeks for this. I really don't get this w..." Harvey: "That seems like a lot of ground to cover in 6 days if you want to stop at all these places" | D8: Itinerary realism delivered bluntly. ComeMorocco should be willing to say a plan does not work, though with more warmth than the source.
A9: SE-008 | B9: Looking to get some riad and location recommendations for New Year in Marrakech. Trying to be as budget conscious as possible. | C9: Artem: "Worth asking about the compulsory New Year dinner, most medina riads add one at 300 to 600 dirham a head." | D9: The kind of insider detail that makes an answer genuinely valuable: a cost the traveller had no way of anticipating, surfaced before they book.
A10: SE-009 | B10: Has anyone experienced difficulties using the ONCF Voyages website to book Al Boraq tickets? The website keeps displaying technical problems or has no results. | C10: Cynthia: "It looks like they only show 60 days of availability. I've been checking every few days for mid-November to become available." Jane: "Apparently it's easier to pay for the tickets if you use a Visa card, the website doesn't like a lot of 'foreign cards'" | D10: Excellent diagnostic answering: the apparent fault is actually a booking window, and the payment tip is the second thing the traveller needed. A generic answer would have missed both.
A11: SE-010 | B11: We have seen recent reports around severe flooding in the Ourika Valley area. Wondering if our tour is likely to go ahead. | C11: Gabriella: "The flooding that you see where they write 'Atlas mountain' is nowhere near where you are going" Janine: "Was there on Sunday. No floods. All as normal." | D11: Local geographic knowledge correcting a media-driven worry. It also shows why on-the-ground reassurance must never be recycled as current information.
A12: SE-011 | B12: My wife wants to know if she could buy some nice tops at the souks that she could wear to dinner. | C12: Anonymous: "I've never found decent clothes in the souks for women. They have a lot of football kits and fake designer stuff but it's mos..." Wendy: "I was hoping the same thing and I didn't find anything that I would feel comfortable wearing" | D12: Honest expectation correction. The helpful answer here is the disappointing one, and ComeMorocco needs to be willing to give it.
... A18: SE-017 | B18: I have been quoted $130 USD a night for a riad in Marrakech. Is this a reasonable price to pay? | C18: Don: "Without a description, how could anyone offer a reasonable opinion?" | D18: A useful reminder that some questions cannot be answered as asked. The right response identifies the missing information rather than inventing an average.
